storyboard/SourceCodePro-Regular.otf
storyboard/__init__.py
storyboard/fflocate.py
storyboard/frame.py
storyboard/metadata.py
storyboard/storyboard.py
storyboard/util.py
storyboard/version.py
storyboard-0.1.9.dist-info/DESCRIPTION.rst
storyboard-0.1.9.dist-info/METADATA
storyboard-0.1.9.dist-info/RECORD
storyboard-0.1.9.dist-info/WHEEL
storyboard-0.1.9.dist-info/entry_points.txt
storyboard-0.1.9.dist-info/metadata.json
storyboard-0.1.9.dist-info/pbr.json
storyboard-0.1.9.dist-info/top_level.txt
