Metadata-Version: 2.0
Name: storyboard
Version: 0.1.9
Summary: Customizable video storyboard generator with metadata report
Home-page: https://github.com/zmwangx/storyboard
Author: Zhiming Wang
Author-email: zmwangx@gmail.com
License: MIT
Keywords: video storyboard metadata thumbnail ffmpeg
Platform: UNKNOWN
Classifier: Development Status :: 5 - Production/Stable
Classifier: Environment :: Console
Classifier: Intended Audience :: End Users/Desktop
Classifier: License :: OSI Approved :: MIT License
Classifier: Natural Language :: English
Classifier: Programming Language :: Python :: 2
Classifier: Programming Language :: Python :: 2.7
Classifier: Programming Language :: Python :: 3
Classifier: Programming Language :: Python :: 3.2
Classifier: Programming Language :: Python :: 3.3
Classifier: Programming Language :: Python :: 3.4
Classifier: Programming Language :: Python :: 3.5
Classifier: Programming Language :: Python :: 3.6
Classifier: Programming Language :: Python :: Implementation :: CPython
Classifier: Programming Language :: Python :: Implementation :: PyPy
Classifier: Topic :: Multimedia :: Video
Requires-Dist: Pillow (>=2.7)
Provides-Extra: doc
Requires-Dist: Pygments (==1.6); extra == 'doc'
Requires-Dist: Sphinx (==1.2.2); extra == 'doc'
Provides-Extra: test
Requires-Dist: coveralls; extra == 'test'
Requires-Dist: nose; extra == 'test'
